temfpy/__init__.py
temfpy/_version.py
temfpy/gutzwiller.py
temfpy/iMPS.py
temfpy/pfaffian.py
temfpy/schmidt_utils.py
temfpy/slater.py
temfpy/testing.py
temfpy/utils.py
temfpy-0.1.0.dist-info/METADATA
temfpy-0.1.0.dist-info/WHEEL
temfpy-0.1.0.dist-info/licenses/LICENSE
temfpy-0.1.0.dist-info/RECORD
