Metadata-Version: 2.4
Name: temfpy
Version: 0.1.0
Summary:             TeMFpy (Tensor Networks for Mean Field States in Python) is a library for             converting mean-field fermionic wavefunctions into matrix product states (MPS).
Author-email: TeMFpy Developers <temfpy@gmail.com>, Simon Hans Hille <simon.hille@physik.uzh.ch>, Attila Szabó <attila.szabo@physik.uzh.ch>
Maintainer-email: TeMFpy Developers <temfpy@gmail.com>, Simon Hans Hille <simon.hille@physik.uzh.ch>, Attila Szabó <attila.szabo@physik.uzh.ch>
License-Expression: MIT
License-File: LICENSE
Keywords: TeNPy,matrix product states,mean-field theory
Classifier: Development Status :: 5 - Production/Stable
Classifier: License :: OSI Approved :: MIT License
Classifier: Operating System :: MacOS
Classifier: Operating System :: Microsoft :: Windows
Classifier: Operating System :: Unix
Classifier: Programming Language :: Python :: 3.11
Classifier: Programming Language :: Python :: 3.12
Classifier: Topic :: Scientific/Engineering
Classifier: Topic :: Scientific/Engineering :: Physics
Requires-Python: >=3.10
Requires-Dist: numpy
Requires-Dist: pfapack
Requires-Dist: physics-tenpy>=1.0.0
Requires-Dist: scipy
Provides-Extra: dev
Requires-Dist: black>=25.1.0; extra == 'dev'
Requires-Dist: docformatter; extra == 'dev'
Provides-Extra: docs
Requires-Dist: myst-nb; extra == 'docs'
Requires-Dist: sphinx-autodoc-typehints; extra == 'docs'
Requires-Dist: sphinx-rtd-theme; extra == 'docs'
Requires-Dist: sphinx>=8.2; extra == 'docs'
